pyDHM/_init_.py
pyDHM/numericalPropagation.py
pyDHM/phaseCompensation.py
pyDHM/phaseShifting.py
pyDHM/utilities.py
pyDHM-1.0.5.dist-info/LICENSE
pyDHM-1.0.5.dist-info/METADATA
pyDHM-1.0.5.dist-info/WHEEL
pyDHM-1.0.5.dist-info/top_level.txt
pyDHM-1.0.5.dist-info/RECORD
