Metadata-Version: 2.1
Name: pyDHM
Version: 1.0.5
Summary: An open-source Python library to numerically recover the complex wavefield information of samples from Digital Holographic Microscopy (DHM)
Home-page: https://github.com/catrujilla/pyDHM
Author: Carlos Trujillo
Author-email: catrujilla@eafit.edu.co
License: MIT
Classifier: License :: OSI Approved :: MIT License
Classifier: Programming Language :: Python :: 3
Classifier: Programming Language :: Python :: 3.7
License-File: LICENSE
Requires-Dist: matplotlib
Requires-Dist: scipy
